lecore/Looger.py
lecore/__init__.py
lecore/Devices/LeBinDev.py
lecore/Devices/ModbusDev.py
lecore/Devices/__init__.py
lecore/Devices/PhaseDet/ComSettings.json
lecore/Devices/PhaseDet/PhaseDet.py
lecore/Devices/PhaseDet/PhaseDetRegs.py
lecore/Devices/PhaseDet/PhaseDet_Modbus.json
lecore/Devices/PhaseDet/UpgradeSettings.json
lecore/Devices/PhaseDet/VisualSettings.json
lecore/Devices/PhaseDet/__init__.py
lecore/Devices/Rftb/ComSettings.json
lecore/Devices/Rftb/Rftb.py
lecore/Devices/Rftb/RftbLeBin.py
lecore/Devices/Rftb/UpgradeSettings.json
lecore/Devices/Rftb/VisualSettings.json
lecore/Devices/Rftb/__init__.py
lecore/Devices/Rftb/rftbRegs.py
lecore/Devices/Rftb/rftb_Modbus.json
lecore/Devices/Rftb/rftb_registers.json
lecore/Devices/RtdEmul/ComSettings.json
lecore/Devices/RtdEmul/RtdEmul.py
lecore/Devices/RtdEmul/RtdEmulRegs.py
lecore/Devices/RtdEmul/RtdEmul_Modbus.json
lecore/Devices/RtdEmul/UpgradeSettings.json
lecore/Devices/RtdEmul/VisualSettings.json
lecore/Devices/RtdEmul/__init__.py
lecore/Devices/VmsRtd/ComSettings.json
lecore/Devices/VmsRtd/UpgradeSettings.json
lecore/Devices/VmsRtd/VMS_RTDRegs.py
lecore/Devices/VmsRtd/VMS_RTD_Modbus.json
lecore/Devices/VmsRtd/VisualSettings.json
lecore/Devices/VmsRtd/VmsRtd.py
lecore/Devices/VmsRtd/__init__.py
lecore/Doc/ModbusTable.py
lecore/Doc/__init__.py
lecore/Fg320/Fg320.py
lecore/Fg320/__init__.py
lecore/LeBin/RegisterMap.py
lecore/LeBin/SerialCom.py
lecore/LeBin/UpgradeFirmware.py
lecore/LeBin/VisualLeBin.py
lecore/LeBin/__init__.py
lecore/TestFrame/CoreTest.py
lecore/TestFrame/ModbusUnitTest.py
lecore/TestFrame/RtuClient.py
lecore/TestFrame/Runner.py
lecore/TestFrame/TestUtils.py
lecore/TestFrame/__init__.py
lecore/VisualModbus/AppLogging.py
lecore/VisualModbus/Crc32.py
lecore/VisualModbus/HelpAbout.py
lecore/VisualModbus/MbClient.py
lecore/VisualModbus/MbUpgrade.py
lecore/VisualModbus/ReadWrite.py
lecore/VisualModbus/RegMap.py
lecore/VisualModbus/TextMbApp.py
lecore/VisualModbus/TextMbAppCss.tcss
lecore-0.1.30.dist-info/LICENSE
lecore-0.1.30.dist-info/METADATA
lecore-0.1.30.dist-info/WHEEL
lecore-0.1.30.dist-info/top_level.txt
lecore-0.1.30.dist-info/RECORD
