Metadata-Version: 2.1
Name: lecore
Version: 0.1.30
Summary: Logic Elements core utilities
Author-email: Jan Bartovský <jan.bartovsky@logicelements.cz>
Project-URL: Homepage, https://github.com/LogicElements/lecore
Keywords: logicelements,looger,development
Classifier: Programming Language :: Python :: 3
Classifier: License :: OSI Approved :: MIT License
Classifier: Operating System :: OS Independent
Requires-Python: >=3.7
License-File: LICENSE
Requires-Dist: pyserial
Requires-Dist: pymodbus
Requires-Dist: unittest-xml-reporting
Provides-Extra: extra
Requires-Dist: PySimpleGUI ~=4.60.5 ; extra == 'extra'
Requires-Dist: python-docx ; extra == 'extra'
